projects/4-client-dynamic-masking-round-robin-arbiter-with-lock-feature/design.sv
module rr_arbiter_locked (
    input  logic       clk,
    input  logic       rst_n,
    input  logic [3:0] req,
    input  logic       lock,
    input  logic       grant_ack,
    output logic [3:0] grant,
    output logic       grant_valid,
    output logic [1:0] grant_id
);

    // Internal state variables
    logic [1:0] ptr, next_ptr;
    logic [3:0] mask;
    logic [3:0] masked_req;
    logic [3:0] next_grant;
    logic       next_grant_valid;
    logic [1:0] next_grant_id;

    // 1. Generate mask: highest priority is (ptr + 1) % 4
    always_comb begin
        case (ptr)
            2'd0:    mask = 4'b1110; // ptr=0 -> priority: 1, 2, 3, 0
            2'd1:    mask = 4'b1100; // ptr=1 -> priority: 2, 3, 0, 1
            2'd2:    mask = 4'b1000; // ptr=2 -> priority: 3, 0, 1, 2
            2'd3:    mask = 4'b0000; // ptr=3 -> priority: 0, 1, 2, 3
            default: mask = 4'b1110;
        endcase
    end

    // 2. Compute masked request
    assign masked_req = req & mask;

    // 3. Dual-priority parallel arbitration logic
    logic [3:0] masked_grant;
    logic [3:0] unmasked_grant;
    logic [3:0] arb_grant;
    logic       arb_valid;
    logic [1:0] arb_id;

    always_comb begin
        // Priority encoder on masked requests (Priority order: 0 -> 1 -> 2 -> 3)
        masked_grant = 4'b0000;
        if (masked_req[0])      masked_grant = 4'b0001;
        else if (masked_req[1]) masked_grant = 4'b0010;
        else if (masked_req[2]) masked_grant = 4'b0100;
        else if (masked_req[3]) masked_grant = 4'b1000;

        // Priority encoder on unmasked requests
        unmasked_grant = 4'b0000;
        if (req[0])             unmasked_grant = 4'b0001;
        else if (req[1])        unmasked_grant = 4'b0010;
        else if (req[2])        unmasked_grant = 4'b0100;
        else if (req[3])        unmasked_grant = 4'b1000;

        // Select masked if any masked bit was set, else wrap around to unmasked
        if (|masked_req) begin
            arb_grant = masked_grant;
            arb_valid = 1'b1;
        end else if (|req) begin
            arb_grant = unmasked_grant;
            arb_valid = 1'b1;
        end else begin
            arb_grant = 4'b0000;
            arb_valid = 1'b0;
        end

        // Encode binary grant_id
        case (arb_grant)
            4'b0001: arb_id = 2'd0;
            4'b0010: arb_id = 2'd1;
            4'b0100: arb_id = 2'd2;
            4'b1000: arb_id = 2'd3;
            default: arb_id = 2'd0;
        endcase
    end

    // 4. Lock resolution and output next-state logic
    always_comb begin
        // Lock condition: lock=1, current grant_valid=1, and current locked client keeps req high
        if (lock && grant_valid && req[grant_id]) begin
            next_grant       = grant;
            next_grant_valid = 1'b1;
            next_grant_id    = grant_id;
        end else begin
            next_grant       = arb_grant;
            next_grant_valid = arb_valid;
            next_grant_id    = arb_id;
        end
    end

    // 5. Pointer next-state logic
    // Pointer updates to granted client index on clock edges where grant_valid=1 and grant_ack=1, provided lock=0
    always_comb begin
        if (grant_valid && grant_ack && !lock) begin
            next_ptr = grant_id;
        end else begin
            next_ptr = ptr;
        end
    end

    // 6. Registered outputs with synchronous active-low reset
    always_ff @(posedge clk) begin
        if (!rst_n) begin
            ptr         <= 2'd0;
            grant       <= 4'b0000;
            grant_valid <= 1'b0;
            grant_id    <= 2'd0;
        end else begin
            ptr         <= next_ptr;
            grant       <= next_grant;
            grant_valid <= next_grant_valid;
            grant_id    <= next_grant_id;
        end
    end

endmodule

projects/4-client-dynamic-masking-round-robin-arbiter-with-lock-feature/testbench.sv
`timescale 1ns/1ps

module rr_arbiter_locked_visible_tb;

    // DUT interface signals using standard Verilog reg/wire types
    reg        clk;
    reg        rst_n;
    reg  [3:0] req;
    reg        lock;
    reg        grant_ack;
    wire [3:0] grant;
    wire       grant_valid;
    wire [1:0] grant_id;

    // Instance of the DUT
    rr_arbiter_locked dut (
        .clk(clk),
        .rst_n(rst_n),
        .req(req),
        .lock(lock),
        .grant_ack(grant_ack),
        .grant(grant),
        .grant_valid(grant_valid),
        .grant_id(grant_id)
    );

    // Capture signals for waveform viewer
    initial begin
        $dumpfile("sim.vcd");
        $dumpvars(0, rr_arbiter_locked_visible_tb);
    end

    // 10 ns clock generation (100 MHz)
    always #5 clk = ~clk;

    // Pure Verilog check task using integer error counter
    integer fail_count;

    task check_outputs;
        input [3:0] exp_grant;
        input       exp_valid;
        input [1:0] exp_id;
        begin
            #1;
            if ((grant !== exp_grant) || 
                (grant_valid !== exp_valid) || 
                (exp_valid && (grant_id !== exp_id))) begin
                $display("[ERROR] at time %0t: Expected grant=%b, valid=%b, id=%0d | Got grant=%b, valid=%b, id=%0d",
                         $time, exp_grant, exp_valid, exp_id, grant, grant_valid, grant_id);
                fail_count = fail_count + 1;
            end
        end
    endtask

    initial begin
        fail_count = 0;
        clk        = 1'b0;
        rst_n      = 1'b0;
        req        = 4'b0000;
        lock       = 1'b0;
        grant_ack  = 1'b0;

        // Hold reset for 3 cycles and release on negedge
        repeat (3) @(posedge clk);
        @(negedge clk);
        rst_n = 1'b1;

        // Verify initial reset state
        check_outputs(4'b0000, 1'b0, 2'd0);

        // ---------------------------------------------------------------------
        // TEST 1: All 4 clients requesting simultaneously (0 -> 1 -> 2 -> 3 -> 0)
        // ---------------------------------------------------------------------
        $display("Starting Test 1: Full round-robin fairness across 4 clients...");
        @(negedge clk);
        req = 4'b1111;
        grant_ack = 1'b1;

        @(posedge clk);
        check_outputs(4'b0001, 1'b1, 2'd0); // Client 0

        @(posedge clk);
        check_outputs(4'b0010, 1'b1, 2'd1); // Client 1

        @(posedge clk);
        check_outputs(4'b0100, 1'b1, 2'd2); // Client 2

        @(posedge clk);
        check_outputs(4'b1000, 1'b1, 2'd3); // Client 3

        @(posedge clk);
        check_outputs(4'b0001, 1'b1, 2'd0); // Wrap around to Client 0

        // ---------------------------------------------------------------------
        // TEST 2: Pointer updates only when grant_valid AND grant_ack are active
        // ---------------------------------------------------------------------
        $display("Starting Test 2: Pointer hold without grant_ack...");
        @(negedge clk);
        grant_ack = 1'b0; // Deassert ack; pointer should not advance

        @(posedge clk);
        check_outputs(4'b0001, 1'b1, 2'd0); // Stays on Client 0

        @(posedge clk);
        check_outputs(4'b0001, 1'b1, 2'd0); // Stays on Client 0

        @(negedge clk);
        grant_ack = 1'b1; // Reassert ack; advance to next

        @(posedge clk);
        check_outputs(4'b0010, 1'b1, 2'd1); // Advances to Client 1

        // ---------------------------------------------------------------------
        // TEST 3: Multi-cycle lock behavior with varying ack sequences
        // ---------------------------------------------------------------------
        $display("Starting Test 3: Multi-cycle lock verification...");
        @(negedge clk);
        lock = 1'b1;      // Lock Client 1
        grant_ack = 1'b1;

        @(posedge clk);
        check_outputs(4'b0010, 1'b1, 2'd1); // Locked on Client 1 with ack

        @(negedge clk);
        grant_ack = 1'b0; // Deassert ack during lock

        @(posedge clk);
        check_outputs(4'b0010, 1'b1, 2'd1); // Retained Client 1 without ack

        @(negedge clk);
        lock = 1'b0;      // Release lock
        grant_ack = 1'b1;

        @(posedge clk);
        check_outputs(4'b0100, 1'b1, 2'd2); // Advances to Client 2

        // ---------------------------------------------------------------------
        // TEST 4: Assertion of lock without an active grant
        // ---------------------------------------------------------------------
        $display("Starting Test 4: Lock assertion with no initial grant...");
        @(negedge clk);
        req = 4'b0000;
        lock = 1'b1;
        grant_ack = 1'b0;

        @(posedge clk);
        check_outputs(4'b0000, 1'b0, 2'd0); // No grant active

        // Request arrives while lock is active; performs normal arbitration
        @(negedge clk);
        req = 4'b1000;

        @(posedge clk);
        check_outputs(4'b1000, 1'b1, 2'd3); // Arbitrated normally to Client 3

        // Clean up
        @(negedge clk);
        lock = 1'b0;
        grant_ack = 1'b1;

        @(posedge clk);
        @(negedge clk);
        req = 4'b0000;
        grant_ack = 1'b0;

        repeat (2) @(posedge clk);
        #1;

        if (fail_count == 0) begin
            $display("[PASS] All verification scenarios passed successfully with 0 errors.");
        end else begin
            $display("[FAIL] Verification completed with %0d errors.", fail_count);
        end

        $finish;
    end

endmodule

projects/4-client-dynamic-masking-round-robin-arbiter-with-lock-feature/waveform.vcd
$date
	Thu Oct  8 10:24:09 2026
$end
$version
	QuestaSim Version 2024.1
$end
$timescale
	1ps
$end

$scope module rr_arbiter_locked_visible_tb $end
$var reg 1 ! clk $end
$var reg 1 " rst_n $end
$var reg 4 # req [3:0] $end
$var reg 1 $ lock $end
$var reg 1 % grant_ack $end
$var wire 1 & grant [3] $end
$var wire 1 ' grant [2] $end
$var wire 1 ( grant [1] $end
$var wire 1 ) grant [0] $end
$var wire 1 * grant_valid $end
$var wire 1 + grant_id [1] $end
$var wire 1 , grant_id [0] $end
$var integer 32 - fail_count $end

$scope task check_outputs $end
$var reg 4 . exp_grant [3:0] $end
$var reg 1 / exp_valid $end
$var reg 2 0 exp_id [1:0] $end
$upscope $end

$scope module dut $end
$var wire 1 1 clk $end
$var wire 1 2 rst_n $end
$var wire 1 3 req [3] $end
$var wire 1 4 req [2] $end
$var wire 1 5 req [1] $end
$var wire 1 6 req [0] $end
$var wire 1 7 lock $end
$var wire 1 8 grant_ack $end
$var reg 4 9 grant [3:0] $end
$var reg 1 : grant_valid $end
$var reg 2 ; grant_id [1:0] $end
$var reg 2 < ptr [1:0] $end
$var reg 2 = next_ptr [1:0] $end
$var reg 4 > mask [3:0] $end
$var reg 4 ? masked_req [3:0] $end
$var reg 4 @ next_grant [3:0] $end
$var reg 1 A next_grant_valid $end
$var reg 2 B next_grant_id [1:0] $end
$var reg 4 C masked_grant [3:0] $end
$var reg 4 D unmasked_grant [3:0] $end
$var reg 4 E arb_grant [3:0] $end
$var reg 1 F arb_valid $end
$var reg 2 G arb_id [1:0] $end
$upscope $end
$var wire 1 & grant [3] $end
$var wire 1 ' grant [2] $end
$var wire 1 ( grant [1] $end
$var wire 1 ) grant [0] $end
$var wire 1 * grant_valid $end
$var wire 1 + grant_id [1] $end
$var wire 1 , grant_id [0] $end

$scope task check_outputs $end
$upscope $end

$scope module dut $end
$var wire 1 1 clk $end
$var wire 1 2 rst_n $end
$var wire 1 3 req [3] $end
$var wire 1 4 req [2] $end
$var wire 1 5 req [1] $end
$var wire 1 6 req [0] $end
$var wire 1 7 lock $end
$var wire 1 8 grant_ack $end
$upscope $end
$upscope $end
$enddefinitions $end
#0
$dumpvars
0!
0"
b0 #
0$
0%
bx 9
x:
bx ;
bx <
bx =
b1110 >
b0 ?
b0 @
0A
b0 B
b0 C
b0 D
b0 E
0F
b0 G
bx .
x/
bx 0
b0 -
x)
x(
x'
x&
x*
x,
x+
08
07
06
05
04
03
02
01
$end
#5000
1!
11
b0 <
b0 9
0:
b0 ;
0*
0,
0+
0)
0(
0'
0&
b0 =
#10000
0!
01
#15000
1!
11
#20000
0!
01
#25000
1!
11
#30000
0!
01
1"
b0 .
0/
b0 0
12
#35000
1!
11
#40000
0!
01
b1111 #
1%
16
15
14
13
18
b1110 ?
b10 C
b1 D
b10 E
1F
b1 G
b10 @
1A
b1 B
#45000
1!
11
b1 .
1/
b10 9
1:
b1 ;
1*
1,
1(
b1 =
#46000
b1 -
#50000
0!
01
#55000
1!
11
b10 .
b1 0
b1 <
b1100 >
b1100 ?
b0 C
b100 C
b0 D
b1 D
b100 E
b10 G
b100 @
b10 B
#60000
0!
01
#65000
1!
11
b100 .
b10 0
b100 9
b10 ;
0,
1+
0(
1'
b10 =
#70000
0!
01
#75000
1!
11
b1000 .
b11 0
b10 <
b1000 >
b1000 ?
b0 C
b1000 C
b0 D
b1 D
b1000 E
b11 G
b1000 @
b11 B
#76000
b10 -
#80000
0!
01
#85000
1!
11
b1 .
b0 0
b1000 9
b11 ;
1,
0'
1&
b11 =
#86000
b11 -
#90000
0!
01
0%
08
b10 =
#95000
1!
11
#96000
b100 -
#100000
0!
01
#105000
1!
11
#106000
b101 -
#110000
0!
01
1%
18
b11 =
#115000
1!
11
b10 .
b1 0
b11 <
b0 >
b0 ?
b0 C
b0 D
b1 D
b1 E
b0 G
b1 @
b0 B
#116000
b110 -
#120000
0!
01
1$
17
b1000 @
b11 B
#125000
1!
11
#126000
b111 -
#130000
0!
01
0%
08
#135000
1!
11
#136000
b1000 -
#140000
0!
01
0$
1%
07
18
b1 @
b0 B
#145000
1!
11
b100 .
b10 0
b1 9
b0 ;
0,
0+
1)
0&
b0 =
#146000
b1001 -
#150000
0!
01
b0 #
1$
0%
06
05
04
03
17
08
b0 D
b0 E
0F
b0 @
0A
b11 =
#155000
1!
11
b0 .
0/
b0 0
b0 9
0:
0)
0*
#160000
0!
01
b1000 #
13
b1000 D
b1000 E
1F
b11 G
b1000 @
1A
b11 B
#165000
1!
11
b1000 .
1/
b11 0
b1000 9
1:
b11 ;
1*
1,
1+
1&
#170000
0!
01
0$
1%
07
18
#175000
1!
11
#180000
0!
01
b0 #
0%
03
08
b0 D
b0 E
0F
b0 G
b0 @
0A
b0 B
#185000
1!
11
b0 9
0:
b0 ;
0*
0,
0+
0&
